mdscaling
