Metadata-Version: 1.1
Name: mdscaling
Version: 0.0.9
Summary: Multi-dimensional network scaling
Home-page: https://github.com/pedroramaciotti/MDScaling
Author: Pedro Ramaciotti Morales
Author-email: pedro.ramaciotti@gmail.com
License: UNKNOWN
Download-URL: https://github.com/pedroramaciotti/MDScaling/archive/0.0.9.tar.gz
Keywords: multi-dimensional scaling,graph compression,dimentionality reduction,representation learning
Platform: UNKNOWN
